tests/__init__.py
tests/validator_test.py
thearbiter/__init__.py
thearbiter/validator.py
The_Arbiter-1.0.0.dist-info/LICENSE
The_Arbiter-1.0.0.dist-info/METADATA
The_Arbiter-1.0.0.dist-info/WHEEL
The_Arbiter-1.0.0.dist-info/top_level.txt
The_Arbiter-1.0.0.dist-info/RECORD
