Metadata-Version: 2.1
Name: The-Arbiter
Version: 1.0.0
Summary: An argument validation library.
Home-page: https://gitlab.com/codejuicer/the-arbiter
Author: Cole Kelley
Author-email: ck@codejuicer.com
License: MIT
Keywords: validation,arguments
Platform: UNKNOWN
Classifier: Programming Language :: Python :: 3
Classifier: License :: OSI Approved :: MIT License
Classifier: Operating System :: OS Independent
Requires-Python: >=3
